bsbgateway/__init__.py
bsbgateway/__main__.py
bsbgateway/bsb2tcp.py
bsbgateway/bsb_gateway.py
bsbgateway/cmd_interface.py
bsbgateway/config_reader.py
bsbgateway/config_ui.py
bsbgateway/gateway_config.py
bsbgateway/manage.py
bsbgateway/single_field_logger.py
bsbgateway/virtual_device.py
bsbgateway/virtual_serial.py
bsbgateway/bsb/__init__.py
bsbgateway/bsb/broetje_isr_plus.py
bsbgateway/bsb/bsb-types.json
bsbgateway/bsb/bsb_comm.py
bsbgateway/bsb/bsb_field.py
bsbgateway/bsb/bsb_telegram.py
bsbgateway/bsb/crc16pure.py
bsbgateway/bsb/errors.py
bsbgateway/bsb/model.py
bsbgateway/bsb/model_filter.py
bsbgateway/bsb/model_merge.py
bsbgateway/bsb/old_bsb_telegram.py
bsbgateway/bsb/payload_decode.py
bsbgateway/bsb/payload_encode.py
bsbgateway/hub/adapter.py
bsbgateway/hub/adapter_settings.py
bsbgateway/hub/event.py
bsbgateway/hub/event_sources.py
bsbgateway/hub/serial_source.py
bsbgateway/hub/tcp_adapter.py
bsbgateway/tools/bsb_field_to_model.py
bsbgateway/tools/extract_types.py
bsbgateway/util/__init__.py
bsbgateway/util/decorator.py
bsbgateway/web_interface/__init__.py
bsbgateway/web_interface/base.html
bsbgateway/web_interface/config.py
bsbgateway/web_interface/field.html
bsbgateway/web_interface/field_dashwidget.html
bsbgateway/web_interface/field_widget.html
bsbgateway/web_interface/group.html
bsbgateway/web_interface/index.html
bsbgateway/web_interface/routes.py
bsbgateway/web_interface/utils.py
bsbgateway/web_interface/static/jquery.js
bsbgateway/web_interface/static/main.css
bsbgateway/web_interface/static/main.js
bsbgateway-1.0.0.dist-info/METADATA
bsbgateway-1.0.0.dist-info/WHEEL
bsbgateway-1.0.0.dist-info/entry_points.txt
bsbgateway-1.0.0.dist-info/licenses/LICENSE
bsbgateway-1.0.0.dist-info/RECORD
