Metadata-Version: 2.4
Name: BsbGateway
Version: 1.0.0
Summary: Read and write data on a BSB (Boiler System Bus)
Author-email: Johannes Loehnert <loehnert.kde@gmx.de>
License-Expression: LGPL-3.0-or-later
License-File: LICENSE
Keywords: BSB,IoT,boiler,heating,home-automation
Classifier: Development Status :: 4 - Beta
Classifier: Environment :: Console
Classifier: Intended Audience :: End Users/Desktop
Classifier: License :: OSI Approved :: GNU Lesser General Public License v3 or later (LGPLv3+)
Classifier: Natural Language :: English
Classifier: Operating System :: OS Independent
Classifier: Programming Language :: Python :: 3
Classifier: Programming Language :: Python :: 3.8
Classifier: Programming Language :: Python :: 3.9
Classifier: Programming Language :: Python :: 3.10
Classifier: Programming Language :: Python :: 3.11
Classifier: Programming Language :: Python :: 3.12
Classifier: Topic :: Home Automation
Classifier: Topic :: System :: Monitoring
Requires-Python: >=3.8
Requires-Dist: attrs
Requires-Dist: cattrs>=24.1.0
Requires-Dist: flask
Requires-Dist: pyserial
Requires-Dist: quickrpc
Provides-Extra: dev
Requires-Dist: black>=23.0; extra == 'dev'
Requires-Dist: flake8>=6.0; extra == 'dev'
Requires-Dist: isort>=5.12; extra == 'dev'
Requires-Dist: pytest-cov>=4.0; extra == 'dev'
Requires-Dist: pytest>=7.0; extra == 'dev'
